pybib/__init__.py
pybib/formatters.py
pybib/main.py
pybib/utils.py
pybib-2.3.2.dist-info/entry_points.txt
pybib-2.3.2.dist-info/LICENSE
pybib-2.3.2.dist-info/WHEEL
pybib-2.3.2.dist-info/METADATA
pybib-2.3.2.dist-info/RECORD
