Metadata-Version: 2.1
Name: pybib
Version: 2.3.2
Summary: Fetch BibTeX citation information, given a Digital Object Identifier
Home-page: https://jgilchrist.github.io/pybib/
License: BSD-3-Clause
Author: Jonathan Gilchrist
Author-email: jonathan.gilchrist@factset.com
Requires-Python: >=3.5
Classifier: License :: OSI Approved :: BSD License
Classifier: Programming Language :: Python :: 3
Classifier: Programming Language :: Python :: 3.5
Classifier: Programming Language :: Python :: 3.6
Classifier: Programming Language :: Python :: 3.7
Classifier: Programming Language :: Python :: 3.8
Requires-Dist: colorama (>=0.4.3,<0.5.0)
Requires-Dist: requests (>=2.24,<3.0)
Project-URL: Repository, https://github.com/jgilchrist/pybib
